CHANGELOG.md
majormode/__init__.py
majormode/perseus/__init__.py
majormode/perseus/constant/__init__.py
majormode/perseus/constant/account.py
majormode/perseus/constant/application.py
majormode/perseus/constant/area.py
majormode/perseus/constant/contact.py
majormode/perseus/constant/date.py
majormode/perseus/constant/http.py
majormode/perseus/constant/locale.py
majormode/perseus/constant/logging.py
majormode/perseus/constant/notification.py
majormode/perseus/constant/obj.py
majormode/perseus/constant/phone.py
majormode/perseus/constant/privacy.py
majormode/perseus/constant/regex.py
majormode/perseus/constant/sort_order.py
majormode/perseus/constant/stage.py
majormode/perseus/constant/team.py
majormode/perseus/constant/url.py
majormode/perseus/model/__init__.py
majormode/perseus/model/api_key.py
majormode/perseus/model/app.py
majormode/perseus/model/connection.py
majormode/perseus/model/contact.py
majormode/perseus/model/country.py
majormode/perseus/model/date.py
majormode/perseus/model/enum.py
majormode/perseus/model/geolocation.py
majormode/perseus/model/label.py
majormode/perseus/model/locale.py
majormode/perseus/model/notification.py
majormode/perseus/model/obj.py
majormode/perseus/model/picture.py
majormode/perseus/model/smtp.py
majormode/perseus/model/version.py
majormode/perseus/utils/__init__.py
majormode/perseus/utils/cast.py
majormode/perseus/utils/egg_util.py
majormode/perseus/utils/file_util.py
majormode/perseus/utils/image_util.py
majormode/perseus/utils/key_util.py
majormode/perseus/utils/logging.py
majormode/perseus/utils/logrotate.py
majormode/perseus/utils/module_utils.py
majormode/perseus/utils/photo_util.py
majormode/perseus/utils/setup_util.py
majormode/perseus/utils/socket_util.py
majormode/perseus/utils/stage.py
majormode/perseus/utils/string_util.py
majormode/perseus/utils/zip_util.py
perseus_core_library-1.20.5.dist-info/LICENSE.md
perseus_core_library-1.20.5.dist-info/WHEEL
perseus_core_library-1.20.5.dist-info/METADATA
perseus_core_library-1.20.5.dist-info/RECORD
