Metadata-Version: 2.1
Name: perseus-core-library
Version: 1.20.5
Summary: Perseus Core Python library
Home-page: https://github.com/majormode/perseus-core-python-library
License: SEE LICENSE IN <LICENSE.md>
Keywords: core,library,perseus
Author: Daniel CAUNE
Author-email: daniel.caune@gmail.com
Requires-Python: >=3.9
Classifier: Development Status :: 5 - Production/Stable
Classifier: License :: Other/Proprietary License
Classifier: Operating System :: OS Independent
Classifier: Programming Language :: Python
Classifier: Programming Language :: Python :: 3
Classifier: Programming Language :: Python :: 3.9
Classifier: Programming Language :: Python :: 3.10
Classifier: Programming Language :: Python :: 3.11
Classifier: Topic :: Software Development :: Libraries
Requires-Dist: exifread (>=3.0.0,<4.0.0)
Requires-Dist: jsonpickle (>=3.0.1,<4.0.0)
Requires-Dist: pillow (>=10.4.0,<11.0.0)
Requires-Dist: pipfile (>=0.0.2,<0.0.3)
Requires-Dist: python-dateutil (>=2.9.0,<3.0.0)
Requires-Dist: pytz (>=2024.1,<2025.0)
Requires-Dist: six (>=1.16.0,<2.0.0)
Requires-Dist: unidecode (>=1.3.6,<2.0.0)
Project-URL: Repository, https://github.com/majormode/perseus-core-python-library
